pysimpledataflow/__init__.py
pysimpledataflow/flow.py
py_simpledataflow-0.1.3.dist-info/LICENSE
py_simpledataflow-0.1.3.dist-info/METADATA
py_simpledataflow-0.1.3.dist-info/WHEEL
py_simpledataflow-0.1.3.dist-info/RECORD
