Metadata-Version: 2.3
Name: py_simpledataflow
Version: 0.1.3
Summary: A simple Python library for processing data through a stream
License: MIT
Author: Arnaud Valmary
Requires-Python: >=3.9,<4.0
Classifier: License :: OSI Approved :: MIT License
Classifier: Programming Language :: Python :: 3
Classifier: Programming Language :: Python :: 3.9
Classifier: Programming Language :: Python :: 3.10
Classifier: Programming Language :: Python :: 3.11
Classifier: Programming Language :: Python :: 3.12
Classifier: Programming Language :: Python :: 3.13
Requires-Dist: py_overinspect (==0.1.0)
Project-URL: Repository, https://github.com/ArnaudValmary/py_simpledataflow
